{
  "contest": {
    "id": "adt_easy_20240424_2",
    "title": "AtCoder Daily Training EASY 2024/04/24 18:00start",
    "url": "https://atcoder.jp/contests/adt_easy_20240424_2"
  },
  "tasks": [
    {
      "id": "abc225_a",
      "label": "A",
      "title": "Distinct Strings",
      "url": "https://atcoder.jp/contests/adt_easy_20240424_2/tasks/abc225_a",
      "directory": {
        "path": "a",
        "testdir": "test",
        "submit": "Main.hs"
      }
    },
    {
      "id": "abc220_a",
      "label": "B",
      "title": "Find Multiple",
      "url": "https://atcoder.jp/contests/adt_easy_20240424_2/tasks/abc220_a",
      "directory": {
        "path": "b",
        "testdir": "test",
        "submit": "Main.hs"
      }
    },
    {
      "id": "abc285_b",
      "label": "C",
      "title": "Longest Uncommon Prefix",
      "url": "https://atcoder.jp/contests/adt_easy_20240424_2/tasks/abc285_b"
    },
    {
      "id": "abc337_b",
      "label": "D",
      "title": "Extended ABC",
      "url": "https://atcoder.jp/contests/adt_easy_20240424_2/tasks/abc337_b"
    },
    {
      "id": "abc228_c",
      "label": "E",
      "title": "Final Day",
      "url": "https://atcoder.jp/contests/adt_easy_20240424_2/tasks/abc228_c"
    }
  ]
}